school_mcp/__init__.py
school_mcp/__main__.py
school_mcp/config.py
school_mcp/deadline_scraper.py
school_mcp/file_downloader.py
school_mcp/reminders.py
school_mcp/server.py
iflow_mcp_54yyyu_school_mcp-0.1.0.dist-info/METADATA
iflow_mcp_54yyyu_school_mcp-0.1.0.dist-info/WHEEL
iflow_mcp_54yyyu_school_mcp-0.1.0.dist-info/entry_points.txt
iflow_mcp_54yyyu_school_mcp-0.1.0.dist-info/top_level.txt
iflow_mcp_54yyyu_school_mcp-0.1.0.dist-info/RECORD
