Metadata-Version: 2.4
Name: iflow-mcp_54yyyu_school-mcp
Version: 0.1.0
Summary: MCP Server for School-related functionalities
Author: Your Name
Author-email: your.email@example.com
Requires-Python: >=3.8
Requires-Dist: mcp>=1.2.0
Requires-Dist: canvasapi
Requires-Dist: gradescopeapi
Requires-Dist: pandas
Requires-Dist: pytz
Requires-Dist: httpx
Requires-Dist: tqdm
Requires-Dist: python-dotenv
Provides-Extra: dev
Requires-Dist: pytest>=7.0.0; extra == "dev"
Requires-Dist: black>=22.3.0; extra == "dev"
Dynamic: author
Dynamic: author-email
Dynamic: requires-python
